ml_playground_attention/__init__.py
ml_playground_attention/_nbdev.py
ml_playground_attention/dataset_ted_en_az.py
ml_playground_attention/model.py
ml_playground_attention-0.1.0.dist-info/WHEEL
ml_playground_attention-0.1.0.dist-info/METADATA
ml_playground_attention-0.1.0.dist-info/RECORD
