Metadata-Version: 2.1
Name: ml-playground-attention
Version: 0.1.0
Summary: 
Author: Cdfghglz
Author-email: cdfghglz@gmail.com
Requires-Python: >=3.6,<4.0
Classifier: Programming Language :: Python :: 3
Classifier: Programming Language :: Python :: 3.6
Classifier: Programming Language :: Python :: 3.7
Classifier: Programming Language :: Python :: 3.8
Classifier: Programming Language :: Python :: 3.9
Requires-Dist: comet-ml (>=3.2.7,<4.0.0)
Requires-Dist: nbdev (>=1.1.5,<2.0.0)
Requires-Dist: tensorflow-gpu (>=2.0.0,<3.0.0)
